sumstats_liftover/__init__.py
sumstats_liftover/chain_files.py
sumstats_liftover/liftover_df.py
sumstats_liftover-1.1.0.dist-info/licenses/LICENSE
sumstats_liftover-1.1.0.dist-info/METADATA
sumstats_liftover-1.1.0.dist-info/WHEEL
sumstats_liftover-1.1.0.dist-info/top_level.txt
sumstats_liftover-1.1.0.dist-info/RECORD
