Metadata-Version: 2.4
Name: sumstats-liftover
Version: 1.1.0
Summary: Fast chain-based liftover for pandas DataFrames
Author-email: Yunye He <gwaslab@gmail.com>
License: MIT
Project-URL: Homepage, https://github.com/yourusername/sumstats-liftover
Project-URL: Repository, https://github.com/yourusername/sumstats-liftover
Project-URL: Issues, https://github.com/yourusername/sumstats-liftover/issues
Keywords: liftover,genomics,bioinformatics,pandas,chain-file
Classifier: Development Status :: 5 - Production/Stable
Classifier: Intended Audience :: Science/Research
Classifier: Topic :: Scientific/Engineering :: Bio-Informatics
Classifier: Programming Language :: Python :: 3
Classifier: Programming Language :: Python :: 3.8
Classifier: Programming Language :: Python :: 3.9
Classifier: Programming Language :: Python :: 3.10
Classifier: Programming Language :: Python :: 3.11
Classifier: Programming Language :: Python :: 3.12
Requires-Python: >=3.8
License-File: LICENSE
Requires-Dist: numpy>=1.20.0
Requires-Dist: pandas>=1.3.0
Provides-Extra: dev
Requires-Dist: pytest>=7.0.0; extra == "dev"
Requires-Dist: pytest-cov>=4.0.0; extra == "dev"
Dynamic: license-file
